orb_models/__init__.py
orb_models/utils.py
orb_models/dataset/ase_dataset.py
orb_models/forcefield/__init__.py
orb_models/forcefield/atomic_system.py
orb_models/forcefield/base.py
orb_models/forcefield/calculator.py
orb_models/forcefield/featurization_utilities.py
orb_models/forcefield/gns.py
orb_models/forcefield/graph_regressor.py
orb_models/forcefield/nn_util.py
orb_models/forcefield/pretrained.py
orb_models/forcefield/property_definitions.py
orb_models/forcefield/rbf.py
orb_models/forcefield/reference_energies.py
orb_models/forcefield/segment_ops.py
orb_models-4.1.0.dist-info/LICENSE
orb_models-4.1.0.dist-info/METADATA
orb_models-4.1.0.dist-info/WHEEL
orb_models-4.1.0.dist-info/top_level.txt
orb_models-4.1.0.dist-info/RECORD
