Metadata-Version: 2.1
Name: orb-models
Version: 4.1.0
Summary: Foundation models for computational chemistry.
Author: Orbital Materials
License: Apache License, Version 2.0
Project-URL: Homepage, https://github.com/orbital-materials/orb-models
Project-URL: Changelog, https://github.com/orbital-materials/orb-models/releases
Project-URL: Issues, https://github.com/orbital-materials/orb-models/issues
Project-URL: CI, https://github.com/orbital-materials/orb-models/actions
Classifier: Programming Language :: Python :: 3
Classifier: Programming Language :: Python :: 3.8
Classifier: Programming Language :: Python :: 3.9
Classifier: Programming Language :: Python :: 3.10
Classifier: Programming Language :: Python :: 3.11
Classifier: Programming Language :: Python :: 3.12
Requires-Python: >=3.8
License-File: LICENSE
Requires-Dist: cached_path>=1.6.2
Requires-Dist: ase>=3.23.0
Requires-Dist: numpy>=1.26.4
Requires-Dist: scipy>=1.13.1
Requires-Dist: torch<3.0.0,>=2.2.0
Requires-Dist: dm-tree>=0.1.8
Requires-Dist: tqdm>=4.66.5
Provides-Extra: test
Requires-Dist: pytest; extra == "test"
